README.md
pyproject.toml
trustgraph/cli_version.py
trustgraph/cli/__init__.py
trustgraph/cli/add_library_document.py
trustgraph/cli/delete_collection.py
trustgraph/cli/delete_config_item.py
trustgraph/cli/delete_flow_blueprint.py
trustgraph/cli/delete_kg_core.py
trustgraph/cli/delete_mcp_tool.py
trustgraph/cli/delete_tool.py
trustgraph/cli/dump_msgpack.py
trustgraph/cli/dump_queues.py
trustgraph/cli/get_config_item.py
trustgraph/cli/get_flow_blueprint.py
trustgraph/cli/get_kg_core.py
trustgraph/cli/graph_to_turtle.py
trustgraph/cli/init_pulsar_manager.py
trustgraph/cli/init_trustgraph.py
trustgraph/cli/invoke_agent.py
trustgraph/cli/invoke_document_rag.py
trustgraph/cli/invoke_graph_rag.py
trustgraph/cli/invoke_llm.py
trustgraph/cli/invoke_mcp_tool.py
trustgraph/cli/invoke_nlp_query.py
trustgraph/cli/invoke_objects_query.py
trustgraph/cli/invoke_prompt.py
trustgraph/cli/invoke_structured_query.py
trustgraph/cli/list_collections.py
trustgraph/cli/list_config_items.py
trustgraph/cli/load_doc_embeds.py
trustgraph/cli/load_kg_core.py
trustgraph/cli/load_knowledge.py
trustgraph/cli/load_pdf.py
trustgraph/cli/load_sample_documents.py
trustgraph/cli/load_structured_data.py
trustgraph/cli/load_text.py
trustgraph/cli/load_turtle.py
trustgraph/cli/put_config_item.py
trustgraph/cli/put_flow_blueprint.py
trustgraph/cli/put_kg_core.py
trustgraph/cli/remove_library_document.py
trustgraph/cli/save_doc_embeds.py
trustgraph/cli/set_collection.py
trustgraph/cli/set_mcp_tool.py
trustgraph/cli/set_prompt.py
trustgraph/cli/set_token_costs.py
trustgraph/cli/set_tool.py
trustgraph/cli/show_config.py
trustgraph/cli/show_flow_blueprints.py
trustgraph/cli/show_flow_state.py
trustgraph/cli/show_flows.py
trustgraph/cli/show_graph.py
trustgraph/cli/show_kg_cores.py
trustgraph/cli/show_library_documents.py
trustgraph/cli/show_library_processing.py
trustgraph/cli/show_mcp_tools.py
trustgraph/cli/show_parameter_types.py
trustgraph/cli/show_processor_state.py
trustgraph/cli/show_prompts.py
trustgraph_cli.egg-info/PKG-INFO
trustgraph_cli.egg-info/SOURCES.txt
trustgraph_cli.egg-info/dependency_links.txt
trustgraph_cli.egg-info/entry_points.txt
trustgraph_cli.egg-info/requires.txt
trustgraph_cli.egg-info/top_level.txt